MANIFEST.in
README.rst
setup.cfg
setup.py
s3_consistency_checker/__init__.py
s3_consistency_checker/cli.py
s3_consistency_checker/comparison.py
s3_consistency_checker/shm.py
s3_consistency_checker/utils.py
s3_consistency_checker.egg-info/PKG-INFO
s3_consistency_checker.egg-info/SOURCES.txt
s3_consistency_checker.egg-info/dependency_links.txt
s3_consistency_checker.egg-info/entry_points.txt
s3_consistency_checker.egg-info/requires.txt
s3_consistency_checker.egg-info/top_level.txt
s3_consistency_checker/s3/__init__.py
s3_consistency_checker/s3/etag.py
s3_consistency_checker/s3/url.py