Metadata-Version: 1.1
Name: s3-consistency-checker
Version: 1.1.0
Summary: Check consistency of files stored on S3 against local files
Home-page: https://github.com/pmuller/s3-consistency-checker
Author: Philippe Muller
Author-email: philippe.muller@gmail.com
License: Apache License 2.0
Keywords: s3
Platform: UNKNOWN
Classifier: Programming Language :: Python :: 3.5
Classifier: Intended Audience :: Developers
Classifier: Development Status :: 5 - Production/Stable
Classifier: Operating System :: POSIX :: Linux
